<?xml version="1.0" encoding="UTF-8"?>
<?xml-stylesheet href="LIBRARY/STYLE.XSL" type="text/xsl" ?><Dimap_Document>
  <Metadata_Identification>
      <METADATA_FORMAT version="2.0">DIMAP</METADATA_FORMAT>
      <METADATA_PROFILE>PHR_SENSOR</METADATA_PROFILE>
      <METADATA_SUBPROFILE>PRODUCT</METADATA_SUBPROFILE>
      <METADATA_LANGUAGE>en</METADATA_LANGUAGE>
  </Metadata_Identification>
  <Dataset_Identification>
      <DATASET_TYPE>RASTER_SENSOR</DATASET_TYPE>
      <DATASET_NAME version="1.0">DS_PHR1A_201303310839218_FR1_PX_E031N41_1208_00725</DATASET_NAME>
      <DATASET_TN_PATH href="ICON_PHR1A_P_201303310839568_SEN_620285101-001.JPG"/>
      <DATASET_TN_FORMAT>image/jpeg</DATASET_TN_FORMAT>
      <DATASET_QL_PATH href="PREVIEW_PHR1A_P_201303310839568_SEN_620285101-001.JPG"/>
      <DATASET_QL_FORMAT>image/jpeg</DATASET_QL_FORMAT>
      <Legal_Constraints>
         <COPYRIGHT>Copyright@2013 CNES</COPYRIGHT>
      </Legal_Constraints>
  </Dataset_Identification>
  <Dataset_Content>
      <SURFACE_AREA unit="square km">203.012</SURFACE_AREA>
      <Dataset_Components>
         <Component>
            <COMPONENT_TITLE>Processing</COMPONENT_TITLE>
            <COMPONENT_CONTENT>Lineage Information</COMPONENT_CONTENT>
            <COMPONENT_TYPE version="2.0">DIMAP</COMPONENT_TYPE>
            <COMPONENT_PATH href="LINEAGE/PROCESSING_PHR1A_P_201303310839568_SEN_620285101-001_DIM.XML"/>
         </Component>
         <Component>
            <COMPONENT_TITLE>Strip Source</COMPONENT_TITLE>
            <COMPONENT_CONTENT>Lineage Information</COMPONENT_CONTENT>
            <COMPONENT_TYPE version="2.0">DIMAP</COMPONENT_TYPE>
            <COMPONENT_PATH href="LINEAGE/STRIP_DS_PHR1A_201303310839568_FR1_PX_E031N41_1208_00729_DIM.XML"/>
         </Component>
         <Component>
            <COMPONENT_TITLE>RPC Model</COMPONENT_TITLE>
            <COMPONENT_CONTENT>Geoposition Model</COMPONENT_CONTENT>
            <COMPONENT_TYPE version="2.0">DIMAP</COMPONENT_TYPE>
            <COMPONENT_PATH href="RPC_PHR1A_P_201303310839568_SEN_620285101-001.XML"/>
         </Component>
      </Dataset_Components>
      <Dataset_Extent>
         <EXTENT_TYPE>Bounding_Polygon</EXTENT_TYPE>
         <Vertex>
            <LON>31.80188848059456</LON>
            <LAT>41.36572078733516</LAT>
            <COL>1</COL>
            <ROW>1</ROW>
         </Vertex>
         <Vertex>
            <LON>32.0773402466064</LON>
            <LAT>41.37445752941984</LAT>
            <COL>40000</COL>
            <ROW>1</ROW>
         </Vertex>
         <Vertex>
            <LON>32.07774210471229</LON>
            <LAT>41.2982934651835</LAT>
            <COL>40000</COL>
            <ROW>15872</ROW>
         </Vertex>
         <Vertex>
            <LON>31.80129386226897</LON>
            <LAT>41.28825129259548</LAT>
            <COL>1</COL>
            <ROW>15872</ROW>
         </Vertex>
         <Center>
            <LON>31.93956617354555</LON>
            <LAT>41.33168076863349</LAT>
            <COL>20000</COL>
            <ROW>7936</ROW>
         </Center>
      </Dataset_Extent>
  </Dataset_Content>
  <Product_Information>
      <Producer_Information>
         <PRODUCER_NAME>SISA</PRODUCER_NAME>
         <PRODUCER_URL href="http://www.spotimage.fr"/>
         <PRODUCER_CONTACT>sales@astrium.eads.net</PRODUCER_CONTACT>
         <PRODUCER_ADDRESS>5 rue des Satellites - BP 14359 - F 31030 Toulouse Cedex 4 - France</PRODUCER_ADDRESS>
      </Producer_Information>
      <Delivery_Identification>
         <PRODUCTION_DATE>2013-05-16T15:38:53.885</PRODUCTION_DATE>
         <JOB_ID>620285101-001</JOB_ID>
         <PRODUCT_CODE>PHR</PRODUCT_CODE>
         <DELIVERY_TYPE>NETWORK</DELIVERY_TYPE>
         <Order_Identification>
            <CUSTOMER_REFERENCE>ASV GEO</CUSTOMER_REFERENCE>
            <INTERNAL_REFERENCE/>
            <COMMERCIAL_REFERENCE>SO13004494-004</COMMERCIAL_REFERENCE>
            <COMMERCIAL_ITEM>4</COMMERCIAL_ITEM>
         </Order_Identification>
      </Delivery_Identification>
  </Product_Information>
  <Coordinate_Reference_System>
      <Geodetic_CRS>
         <CRS_TABLES version="6.3">EPSG</CRS_TABLES>
         <GEODETIC_CRS_TYPE>GEOGRAPHIC2D</GEODETIC_CRS_TYPE>
         <GEODETIC_CRS_NAME>WGS84</GEODETIC_CRS_NAME>
         <GEODETIC_CRS_CODE>urn:ogc:def:crs:EPSG::4326</GEODETIC_CRS_CODE>
      </Geodetic_CRS>
      <Temporal_CRS>
         <CRS_TABLES version="0.0">ITU</CRS_TABLES>
         <TEMPORAL_CRS_NAME>UTC</TEMPORAL_CRS_NAME>
      </Temporal_CRS>
  </Coordinate_Reference_System>
  <Geoposition>
      <Raster_CRS>
         <RASTER_GEOMETRY>SENSOR</RASTER_GEOMETRY>
         <PIXEL_ORIENTATION>CENTER</PIXEL_ORIENTATION>
         <PIXEL_CRS_TYPE>POINT</PIXEL_CRS_TYPE>
         <PIXEL_ORIGIN>1</PIXEL_ORIGIN>
      </Raster_CRS>
      <Geoposition_Models>
         <Rational_Function_Model>
            <Component>
               <COMPONENT_TITLE>RPC Model</COMPONENT_TITLE>
               <COMPONENT_CONTENT>Geoposition Model</COMPONENT_CONTENT>
               <COMPONENT_TYPE version="2.0">DIMAP</COMPONENT_TYPE>
               <COMPONENT_PATH href="RPC_PHR1A_P_201303310839568_SEN_620285101-001.XML"/>
            </Component>
         </Rational_Function_Model>
      </Geoposition_Models>
  </Geoposition>
  <Processing_Information>
      <Production_Facility>
         <SOFTWARE version="V_03_08">IPU V_03_08</SOFTWARE>
         <PROCESSING_CENTER>FCMUGC</PROCESSING_CENTER>
         <PROCESSING_PLACE/>
      </Production_Facility>
      <Product_Settings>
         <PROCESSING_LEVEL>SENSOR</PROCESSING_LEVEL>
         <SPECTRAL_PROCESSING>P</SPECTRAL_PROCESSING>
         <Geometric_Settings>
            <GEOMETRIC_PROCESSING>SENSOR</GEOMETRIC_PROCESSING>
            <EPHEMERIS_USED>CORRECTED</EPHEMERIS_USED>
            <ATTITUDES_USED>ACCURATE</ATTITUDES_USED>
            <GROUND_SETTING>false</GROUND_SETTING>
            <VERTICAL_SETTING>false</VERTICAL_SETTING>
         </Geometric_Settings>
         <Radiometric_Settings>
            <RADIOMETRIC_PROCESSING>BASIC</RADIOMETRIC_PROCESSING>
            <INTER_DETECTOR_NORMALIZATION>false</INTER_DETECTOR_NORMALIZATION>
            <DETECTORS_INTERPOLATION>true</DETECTORS_INTERPOLATION>
            <STRAYLIGHT_CORRECTION>false</STRAYLIGHT_CORRECTION>
            <VCTI_CORRECTION>false</VCTI_CORRECTION>
            <INTER_ARRAY_RECONSTRUCTION>true</INTER_ARRAY_RECONSTRUCTION>
            <RADIOMETRIC_STRETCH>false</RADIOMETRIC_STRETCH>
            <OUT_OF_ORDER_THRESHOLD>0.5</OUT_OF_ORDER_THRESHOLD>
         </Radiometric_Settings>
         <Sampling_Settings>
            <RESAMPLING_SPACING unit="m">0.578772154633125</RESAMPLING_SPACING>
            <RESAMPLING_KERNEL>SPLINE</RESAMPLING_KERNEL>
         </Sampling_Settings>
         <MTF_Settings>
            <PAN_RESTORATION>true</PAN_RESTORATION>
            <MS_RESTORATION>false</MS_RESTORATION>
         </MTF_Settings>
      </Product_Settings>
      <Processing_Lineage>
         <Component>
            <COMPONENT_TITLE>Processing</COMPONENT_TITLE>
            <COMPONENT_CONTENT>Lineage Information</COMPONENT_CONTENT>
            <COMPONENT_TYPE version="2.0">DIMAP</COMPONENT_TYPE>
            <COMPONENT_PATH href="LINEAGE/PROCESSING_PHR1A_P_201303310839568_SEN_620285101-001_DIM.XML"/>
         </Component>
      </Processing_Lineage>
  </Processing_Information>
  <Raster_Data>
      <Data_Access>
         <DATA_FILE_ORGANISATION>BAND_COMPOSITE</DATA_FILE_ORGANISATION>
         <DATA_FILE_FORMAT>image/tiff</DATA_FILE_FORMAT>
         <DATA_FILE_TILES>true</DATA_FILE_TILES>
         <Data_Files>
            <Data_File tile_R="1" tile_C="1">
               <DATA_FILE_PATH href="IMG_PHR1A_P_201303310839568_SEN_620285101-001_R1C1.TIF"/>
            </Data_File>
            <Data_File tile_R="1" tile_C="2">
               <DATA_FILE_PATH href="IMG_PHR1A_P_201303310839568_SEN_620285101-001_R1C2.TIF"/>
            </Data_File>
         </Data_Files>
      </Data_Access>
      <Raster_Dimensions>
         <NROWS>15872</NROWS>
         <NCOLS>40000</NCOLS>
         <NBANDS>1</NBANDS>
         <Tile_Set>
            <NTILES>2</NTILES>
            <Regular_Tiling>
               <NTILES_SIZE nrows="15872" ncols="32000"/>
               <NTILES_COUNT ntiles_R="2" ntiles_C="1"/>
               <OVERLAP_ROW>0</OVERLAP_ROW>
               <OVERLAP_COL>0</OVERLAP_COL>
            </Regular_Tiling>
         </Tile_Set>
      </Raster_Dimensions>
      <Raster_Encoding>
         <DATA_TYPE>INTEGER</DATA_TYPE>
         <NBITS>16</NBITS>
         <SIGN>UNSIGNED</SIGN>
         <COMPRESSION_TYPE>LOSSLESS</COMPRESSION_TYPE>
      </Raster_Encoding>
      <Raster_Display>
         <Band_Display_Order>
            <RED_CHANNEL>P</RED_CHANNEL>
            <GREEN_CHANNEL>P</GREEN_CHANNEL>
            <BLUE_CHANNEL>P</BLUE_CHANNEL>
         </Band_Display_Order>
         <Special_Value>
            <SPECIAL_VALUE_TEXT>NODATA</SPECIAL_VALUE_TEXT>
            <SPECIAL_VALUE_COUNT>0</SPECIAL_VALUE_COUNT>
         </Special_Value>
         <Special_Value>
            <SPECIAL_VALUE_TEXT>SATURATED</SPECIAL_VALUE_TEXT>
            <SPECIAL_VALUE_COUNT>4095</SPECIAL_VALUE_COUNT>
         </Special_Value>
      </Raster_Display>
  </Raster_Data>
  <Radiometric_Data>
      <Dynamic_Range>
         <ACQUISITION_RANGE>12</ACQUISITION_RANGE>
         <PRODUCT_RANGE>12</PRODUCT_RANGE>
      </Dynamic_Range>
      <Histogram_Band_List>
         <Histogram_Band>
            <BAND_ID>P</BAND_ID>
            <VALUES>0 5 0 0 0 0 0 0 0 0 0 0 0 0 1 0 0 0 0 0 0 0 0 0 0 0 0 0 0 0 0 0 0 0 0 0 0 0 0 1 0 0 0 0 0 0 0 0 0 0 0 0 0 0 0 1 0 0 1 1 0 0 1 0 0 0 0 0 0 0 0 0 0 0 0 0 0 0 0 0 0 0 0 0 0 0 0 0 0 0 0 0 0 0 0 0 1 0 1 0 0 1 0 0 1 1 0 0 0 1 0 0 0 0 0 0 0 1 0 1 0 0 0 0 0 0 1 0 0 0 0 0 0 0 0 0 1 0 0 0 0 0 0 0 0 0 0 0 0 0 0 0 0 0 0 0 1 0 3 1 0 0 1 0 1 0 0 0 0 1 1 2 0 0 0 0 0 1 3 0 1 1 1 0 0 2 3 0 2 1 5 5 3 9 11 18 22 54 70 136 171 275 397 527 766 1070 1342 1727 2332 2773 3390 4120 4983 6006 7016 8152 9457 11189 12714 14744 16825 19315 21916 24974 28008 31406 35153 39863 43780 48628 53587 58433 63511 68694 73910 79725 85503 90855 96327 101701 107938 113680 119618 125473 131738 137400 143596 149081 154732 161311 167023 172672 179436 184954 191135 197472 203128 210132 216254 222037 229030 235605 241601 247477 254543 261524 267009 273494 281129 287677 292472 299857 306396 313054 319885 326544 332742 338616 346292 353428 360572 366636 373018 379528 387488 392797 400915 407157 415680 421082 427760 435704 442506 449656 456351 465072 470731 478498 487952 494053 501515 509350 516941 524376 533105 540757 548556 557840 565402 574717 582307 591753 600245 609309 617971 626482 635603 646603 654879 663754 674332 684116 692275 704385 714301 723510 734695 744203 753966 763791 775007 785454 796213 806237 818642 827287 840367 849219 862270 873333 884562 894921 908310 918295 930286 942463 951929 964576 974801 988342 1000978 1010738 1025488 1034583 1048261 1060740 1072504 1086330 1097270 1110710 1122716 1135696 1145804 1159112 1171079 1183958 1198340 1207531 1220022 1232926 1247299 1257422 1269587 1281494 1294925 1305825 1316890 1331035 1342562 1355899 1367690 1380274 1393693 1404067 1417506 1428792 1441219 1454174 1467940 1479868 1494337 1505792 1517248 1530706 1544309 1557120 1566214 1581724 1591248 1606484 1619291 1629935 1641913 1655399 1668147 1680896 1691559 1704088 1714929 1727655 1739111 1752262 1765434 1777926 1789791 1799583 1811216 1825764 1834377 1845532 1860182 1870795 1881142 1892114 1904406 1914475 1923684 1933247 1945504 1956154 1967885 1977396 1987924 1997071 2005349 2015188 2021791 2030768 2041551 2045408 2056488 2066060 2075282 2078061 2088870 2093984 2098739 2109569 2116563 2120884 2130127 2136977 2143026 2149899 2156495 2162910 2166000 2170763 2177350 2183183 2188678 2194456 2194871 2202698 2207201 2211272 2217846 2220607 2225556 2229301 2232470 2237930 2237589 2239472 2244264 2250402 2249109 2251288 2257993 2259406 2262382 2260782 2264126 2265594 2270073 2269955 2271039 2274349 2274039 2277374 2277552 2279320 2280282 2281886 2279555 2279324 2282060 2281434 2276824 2277481 2277984 2277963 2276845 2274341 2276594 2274373 2272786 2273796 2272416 2268309 2268990 2268091 2268980 2267802 2265250 2262764 2263124 2264854 2259256 2261905 2257819 2260909 2255114 2256750 2254102 2251947 2250045 2249772 2250772 2246826 2241947 2241555 2239802 2236694 2235513 2230059 2229501 2225456 2225533 2219796 2216571 2212050 2209340 2206088 2201788 2194664 2188674 2188201 2181750 2176482 2169921 2167185 2161337 2152553 2145498 2139648 2133073 2127956 2120095 2111121 2102113 2092517 2085350 2074352 2065373 2055758 2047244 2033852 2027166 2014363 2002210 1990332 1981646 1969477 1955210 1945458 1930902 1919740 1908799 1898856 1883434 1869058 1855514 1842775 1829544 1814739 1800723 1786740 1772484 1759381 1744341 1731240 1714357 1699072 1683251 1672017 1651218 1636003 1622500 1606974 1591048 1574877 1558329 1540486 1527097 1508406 1493568 1475447 1457885 1440966 1425153 1409278 1392190 1373769 1357665 1342504 1322520 1305474 1288048 1272733 1256285 1240516 1222439 1203649 1186225 1169277 1152612 1135089 1117804 1102578 1084240 1068476 1050321 1032398 1014917 999634 983401 968400 951567 934933 917717 903879 884006 871852 855877 841400 825153 810046 794602 779766 765652 750395 736681 722194 708243 694943 681974 668155 654760 643317 629539 618736 606488 593169 581565 571433 557876 547326 536886 525244 515178 504830 495246 483287 473911 463831 454502 444719 435776 427209 417729 409761 400663 391099 383889 375834 366770 359245 352051 345575 336956 330566 323646 315849 309624 303042 296254 289757 283631 278203 272415 266365 260097 254647 249595 242934 238563 233095 228783 223661 219393 214107 208614 205232 200545 196454 192019 188597 183602 179169 176145 172813 169594 165608 162259 159812 155147 152446 150343 146589 143642 140303 138473 135287 133092 130044 127716 125450 123214 120899 119000 116290 114953 112561 110252 108424 106417 104012 102794 99828 98577 96784 95060 93402 91710 89563 87974 86309 84921 83113 81407 80240 78408 77367 75538 74264 72987 71680 70591 68887 67844 67225 65313 64813 63662 62011 60811 60511 59670 58223 57696 56152 55619 54825 53502 53390 52229 51914 50932 50003 49494 48359 47724 47312 46617 45971 45647 44630 44359 43201 42463 42470 41643 40913 40609 39750 39495 38852 38440 38291 37316 37166 36323 35833 35445 34885 35024 34280 33818 33371 32552 32339 31953 31506 31422 30860 30470 30228 29713 29650 29221 28818 28828 28264 27743 27693 27502 26916 26852 26448 26449 25723 25368 25282 24912 24772 24368 24410 23810 23649 23652 23060 22991 22818 22773 22309 22227 21665 21639 21311 21343 20905 20706 20737 20166 20260 20190 19934 19707 19543 19303 19239 19021 18840 18649 18550 18262 18152 17893 17867 17379 17558 17216 17071 16908 17020 16613 16340 16272 15967 15812 15881 15759 15797 15509 15412 15090 14855 14844 14665 14461 14335 14365 14211 14000 14081 13733 13325 13444 13354 13251 12982 12997 12817 12567 12718 12320 12005 11979 12110 12013 12022 11574 11517 11337 11319 10985 11067 11007 10745 10773 10685 10571 10393 10339 10216 10113 9881 9988 9683 9760 9638 9519 9362 9011 9351 9149 8944 9059 8949 8590 8739 8453 8441 8418 8336 7955 8104 7913 7822 7869 7819 7682 7734 7394 7483 7287 7267 7043 7001 7056 6904 6851 6872 6562 6501 6656 6625 6533 6369 6442 6204 6073 6158 6150 6036 5958 5957 5916 5712 5636 5520 5671 5561 5429 5441 5322 5350 5320 5071 5164 4985 5086 5027 4900 4825 4691 4758 4625 4663 4525 4608 4522 4408 4351 4336 4350 4227 4270 4178 4173 4029 3959 3976 3902 3769 3946 3721 3778 3700 3665 3728 3613 3613 3494 3553 3481 3418 3267 3315 3290 3182 3241 3184 3212 3150 3157 3060 3071 3024 3034 2943 2998 2847 2839 2829 2756 2760 2675 2744 2630 2695 2599 2627 2662 2500 2510 2478 2468 2478 2471 2448 2344 2427 2391 2401 2345 2296 2164 2202 2195 2236 2107 2135 2055 2177 2055 2125 2116 2012 1982 1969 1963 1911 1972 1939 1952 1899 1921 1799 1908 1848 1868 1855 1822 1821 1762 1764 1749 1666 1670 1786 1719 1684 1596 1691 1647 1704 1617 1637 1568 1525 1592 1559 1518 1516 1488 1538 1556 1589 1489 1484 1509 1473 1442 1505 1501 1484 1456 1380 1397 1387 1342 1374 1453 1428 1430 1390 1328 1416 1353 1313 1327 1353 1300 1273 1259 1282 1255 1325 1264 1277 1245 1212 1292 1228 1231 1214 1242 1207 1206 1208 1157 1164 1137 1155 1113 1161 1114 1093 1188 1122 1114 1020 1080 1052 1053 1036 1102 1024 1041 1053 1029 1032 987 1014 952 1022 997 989 951 969 965 980 963 960 931 905 883 980 902 887 889 899 880 948 866 912 836 876 847 828 841 811 869 824 799 833 854 790 791 773 748 771 788 777 764 763 753 778 748 758 737 697 743 706 725 739 724 749 748 736 700 693 688 691 676 670 650 717 640 684 615 660 632 608 638 638 618 631 644 649 657 589 599 640 583 580 600 570 563 573 558 594 606 558 543 564 568 537 518 574 570 529 528 545 543 554 514 495 496 563 546 569 484 550 493 487 509 497 510 468 505 549 498 501 483 450 472 450 445 490 472 438 497 492 500 475 500 462 478 485 472 465 457 493 441 427 430 441 493 462 459 444 466 455 420 428 460 414 435 424 403 443 403 447 445 426 448 369 410 430 412 422 425 415 435 453 397 387 406 397 413 400 396 436 388 384 390 364 400 381 345 387 350 392 392 406 387 371 373 404 346 389 352 369 363 365 389 364 382 382 378 399 423 351 380 342 350 344 364 319 350 335 361 319 316 343 373 324 329 341 299 340 346 323 318 306 351 342 337 339 302 329 329 302 334 325 322 328 314 317 300 281 304 303 329 302 295 309 292 300 279 287 292 266 305 328 293 313 314 282 270 251 289 256 305 289 277 272 245 264 285 264 259 276 249 260 268 267 253 262 245 257 224 254 227 268 245 231 237 235 231 258 245 239 253 258 235 251 237 242 227 291 216 228 241 211 224 237 238 238 236 219 214 214 222 235 241 228 225 203 190 219 201 197 225 226 194 219 211 210 201 205 232 205 199 205 215 221 197 191 214 214 174 203 205 182 195 220 211 225 193 188 177 179 200 203 186 203 174 196 194 200 187 200 179 192 204 182 221 165 202 199 197 179 188 201 204 197 174 177 201 223 190 186 195 178 194 211 182 201 233 234 248 193 217 190 192 209 205 190 209 224 193 212 218 211 210 190 236 232 195 227 216 214 190 213 203 225 230 213 206 231 230 212 216 231 230 207 221 238 202 218 205 204 195 190 209 187 222 184 189 217 182 207 195 181 170 187 170 197 183 195 200 175 189 189 187 172 184 178 178 169 157 162 150 182 175 155 160 171 133 141 153 153 172 145 144 140 131 130 136 137 146 132 152 132 154 154 149 136 136 147 150 138 133 123 118 123 116 126 132 123 87 113 119 132 125 121 115 92 109 106 118 112 111 115 105 108 122 112 90 109 106 105 103 112 118 97 101 100 100 106 94 113 98 112 106 98 94 83 102 93 114 91 104 103 96 93 81 88 80 86 71 81 101 104 74 91 89 110 91 93 78 79 68 90 89 75 74 91 88 81 80 98 64 80 90 80 80 84 76 100 76 70 77 84 87 78 88 82 76 81 76 78 86 78 91 73 69 72 81 80 77 90 89 84 74 69 69 84 76 83 85 77 65 76 87 72 85 82 75 96 75 79 84 55 72 59 73 69 74 85 74 66 89 73 78 80 68 81 74 90 83 84 61 64 86 83 77 69 85 62 73 80 74 84 77 71 88 81 66 69 76 71 66 76 78 77 74 57 77 85 55 79 88 85 84 63 80 85 75 65 80 63 73 60 70 57 48 49 59 67 58 53 72 65 66 43 59 55 56 53 44 57 57 48 57 55 57 60 44 68 62 58 58 52 52 53 49 52 47 51 57 53 60 55 63 54 41 44 57 44 49 58 31 58 51 49 53 45 56 53 49 55 52 49 57 57 49 51 37 56 56 51 58 49 51 44 52 62 58 44 41 64 46 62 62 56 62 53 66 70 59 62 55 62 49 71 63 64 60 57 60 52 51 52 50 62 41 53 57 40 69 70 71 53 72 45 56 41 48 51 57 44 58 57 56 58 54 60 49 42 52 58 44 54 58 48 54 55 50 44 49 51 46 41 55 38 34 45 30 46 36 47 37 35 51 34 41 42 28 38 36 43 32 34 33 40 37 38 24 39 29 40 34 33 37 35 29 48 39 35 26 39 34 41 37 36 31 41 32 24 31 22 27 38 24 32 27 42 38 30 40 46 30 31 38 31 29 38 20 37 29 29 35 33 27 38 30 31 36 21 32 28 40 34 29 24 24 39 35 36 35 26 26 41 37 30 35 34 35 36 39 43 44 36 38 46 40 34 33 33 47 28 52 46 46 43 60 40 46 60 52 43 52 35 40 57 32 48 44 41 47 51 47 47 50 47 41 56 41 43 42 46 43 55 55 49 43 48 47 36 46 42 53 57 43 50 51 35 51 47 50 46 43 53 51 57 39 54 49 57 51 45 59 44 44 54 61 69 54 55 60 59 61 51 56 56 65 43 54 62 47 48 48 34 44 51 45 40 44 56 35 36 47 44 42 50 46 35 37 34 58 38 44 33 38 40 41 32 40 39 39 30 25 34 31 47 28 32 36 35 30 23 30 26 39 36 25 24 32 33 27 30 23 27 26 25 24 39 23 21 26 33 21 25 20 24 28 21 25 25 22 24 30 27 18 24 26 20 19 19 27 17 12 17 19 17 14 20 20 20 16 21 21 29 26 19 28 17 23 22 15 22 14 30 22 20 19 21 19 20 24 28 17 21 18 18 18 18 18 20 20 14 13 17 20 21 16 18 15 22 14 14 18 15 24 12 16 18 13 11 23 23 19 17 15 13 16 15 13 15 13 11 19 19 12 11 13 12 5 11 11 14 11 13 14 18 14 18 14 7 21 16 11 7 14 9 11 12 9 4 12 16 11 7 14 10 7 16 13 8 18 12 13 7 2 11 6 5 8 4 5 10 10 6 9 12 5 14 8 11 8 9 8 5 11 9 5 7 8 14 14 10 10 6 10 11 3 11 6 6 9 12 7 12 9 13 13 9 11 9 9 10 8 12 4 4 15 7 6 9 4 9 10 5 10 7 4 10 10 8 5 11 12 2 10 7 6 11 7 4 6 2 6 14 10 7 13 11 5 7 4 6 4 9 8 6 8 5 5 5 3 6 7 8 0 12 9 3 6 6 5 5 8 3 6 5 6 1 6 13 3 4 8 6 7 5 6 5 9 5 6 2 12 8 2 8 7 6 2 6 8 4 8 7 7 3 6 6 4 1 3 6 10 5 4 5 7 6 2 5 6 2 7 2 5 5 4 8 2 5 7 9 5 5 3 2 4 2 3 3 3 2 5 6 5 2 9 2 7 2 3 4 5 8 10 6 4 5 9 3 5 12 13 11 4 8 1 8 7 7 6 7 1 9 7 8 4 4 6 9 4 6 4 5 7 3 3 5 7 9 7 6 4 3 5 1 3 7 8 5 8 4 6 5 12 2 1 4 8 3 5 5 7 5 5 6 5 10 7 8 2 7 8 6 7 7 13 9 7 8 5 5 6 3 4 4 5 8 13 6 8 6 5 7 8 8 4 11 4 5 5 6 4 7 6 9 9 5 1 11 9 3 6 5 7 7 6 4 7 1 7 0 4 6 3 5 5 4 1 5 6 5 5 9 11 7 3 2 6 4 7 4 4 9 5 5 3 0 3 4 5 5 4 2 4 2 5 5 5 0 5 6 3 1 3 2 5 4 6 4 3 3 1 7 3 5 4 2 2 1 1 3 4 2 3 1 5 5 3 5 4 3 5 2 5 3 3 3 7 0 7 6 3 2 5 4 2 3 4 3 5 2 5 6 2 3 3 2 4 2 3 4 5 5 7 4 4 6 5 7 2 5 5 2 5 1 3 4 3 1 5 10 9 4 3 1 1 1 1 5 3 3 4 3 3 1 1 2 3 4 2 1 4 5 5 2 5 3 3 1 4 3 2 1 2 5 4 1 2 3 3 2 2 4 3 1 4 7 2 4 3 1 4 1 3 0 0 4 7 1 5 2 3 3 1 5 2 2 3 4 0 6 4 3 7 4 3 6 4 4 2 1 5 4 3 2 8 4 0 3 3 4 2 4 2 1 1 1 3 5 3 0 2 4 1 5 1 2 4 0 3 3 7 0 3 6 5 3 2 3 5 1 4 2 2 2 3 0 5 1 3 4 0 0 3 4 4 3 4 7 1 2 2 2 2 0 4 2 3 1 0 3 1 1 4 3 6 2 2 2 1 1 3 4 2 0 3 1 0 2 4 3 3 5 1 2 2 2 2 5 2 5 4 1 3 3 5 1 3 2 3 7 2 1 1 3 6 1 2 3 6 3 0 0 1 3 2 2 4 2 3 2 3 3 4 4 1 2 1 1 2 2 4 1 2 1 6 3 3 1 3 7 3 3 6 1 6 4 1 6 2 5 2 5 0 7 4 4 5 2 3 4 2 2 4 7 0 4 2 3 2 1 5 5 3 4 2 2 3 2 2 3 6 6 3 4 2 4 6 2 3 2 3 4 4 3 0 4 4 5 3 2 1 2 3 3 5 3 1 5 5 3 6 3 0 2 4 1 5 2 4 2 7 1 3 1 7 3 1 2 1 4 3 4 5 4 5 2 2 4 4 2 4 4 4 2 1 4 2 4 3 3 3 2 5 3 3 1 4 3 1 4 2 1 2 4 4 4 3 2 1 6 3 3 4 3 5 2 4 3 2 2 3 6 3 3 3 2 3 2 3 5 3 1 5 2 5 6 2 3 2 1 4 1 1 2 2 7 7 5 3 5 2 4 9 2 2 5 2 3 3 0 4 0 4 1 1 3 5 2 1 3 7 4 3 5 4 5 3 2 1 0 5 1 1 3 4 5 1 1 7 8 5 4 2 6 1 2 3 4 7 2 0 4 0 1 1 6 4 0 1 3 2 2 2 3 2 2 5 2 6 3 1 2 4 5 0 3 3 0 2 3 2 5 5 4 2 3 1 5 0 2 1 1 3 1 4 5 2 3 2 0 4 1 2 3 2 2 2 4 4 1 2 5 2 4 8 1 1 3 2 4 3 1 3 4 3 2 2 2 3 4 3 4 2 3 2 3 1 2 2 1 2 2 4 3 3 1 0 4 4 4 3 2 1 2 2 3 2 2 3 3 1 2 2 4 6 2 3 2 4 0 2 2 3 4 3 1 3 5 3 4 4 1 4 3 0 3 4 4 3 2 7 5 4 0 2 2 4 5 1 1 3 2 3 1 2 2 2 0 3 6 1 2 4 3 5 1 4 2 5 1 1 2 2 6 3 2 2 5 1 2 2 0 1 4 1 2 1 5 0 2 3 5 2 4 1 4 3 2 3 1 4 0 3 6 6 2 2 3 2 3 2 2 2 1 1 3 0 2 6 2 3 2 1 1 4 1 2 2 3 1 1 2 0 3 1 3 2 2 3 2 3 2 0 3 1 1 3 4 2 3 4 2 3 4 3 1 3 2 1 2 0 1 2 1 5 2 1 4 6 3 2 3 4 4 1 1 3 2 1 2 0 2 0 1 4 5 1 4 3 1 4 1 2 0 0 4 3 2 3 3 1 3 6 4 2 2 6 1 3 1 5 1 6 1 2 2 3 4 4 3 6 5 3 4 2 1 3 1 4 2 3 4 3 2 3 0 7 0 0 4 1 2 3 4 3 1 4 1 2 2 3 4 6 0 1 3 0 2 2 2 3 1 3 3 2 4 2 3 2 4 3 1 1 5 0 2 3 1 2 3 4 3 1 3 1 4 2 3 4 3 6 0 0 2 3 1 1 1 4 4 3 2 3 2 3 4 0 0 5 5 2 3 1 1 5 5 2 2 1 2 2 2 1 3 5 7 4 2 3 6 5 3 2 2 2 1 2 2 1 4 3 1 3 2 1 5 0 2 0 2 3 1 0 5 3 0 4 7 2 4 3 4 3 1 2 0 2 4 3 2 2 0 1 2 5 2 2 1 1 1 3 3 2 3 1 3 2 3 0 3 2 1 0 5 4 0 1 3 3 3 2 2 2 7 2 6 1 2 3 4 2 5 1 1 1 4 1 1 1 3 4 3 4 2 1 2 2 2 2 6 2 2 6 3 4 2 2 1 1 4 1 2 3 3 2 2 2 0 2 5 3 3 4 3 1 2 1 1 3 1 5 3 1 3 2 3 2 6 2 3 3 3 3 2 3 3 4 5 4 0 4 1 3 1 0 0 3 2 2 1 3 2 4 2 2 4 2 0 1 2 1 1 3 2 2 3 1 4 3 3 0 5 2 2 1 3 5 3 0 1 2 4 2 2 3 1 4 1 2 0 3 2 2 0 3 2 4 5 1 3 1 2 4 3 3 1 2 2 4 0 4 2 0 1 5 5 1 2 2 2 2 3 5 3 5 3 3 3 4 1 4 3 2 3 6 1 2 0 1 0 2 4 3 2 2 2 2 4 2 4 3 2 0 3 1 2 2 2 3 1 0 2 4 1 1 4 2 2 4 1 0 2 1 3 0 3 5 1 3 5 2 2 5 5 2 6 4 6 1 1 1 1 4 5 0 3 2 0 1 3 3 2 1 3 1 3 3 2 5 3 3 7 1 4 4 1 2 2 5 4 1 3 1 5 2 5 6 2 3 5 6 9 9 5 5 4 5 8 5 5 4 2 8 6 6 6 9 4 10 9 14 12 13 12 16 10 16 21 20 22 28 18 30 31 31 27 24 42 48 0</VALUES>
            <MIN>1</MIN>
            <MAX>4094</MAX>
            <MEAN>495.586</MEAN>
            <STDV>108.457</STDV>
         </Histogram_Band>
      </Histogram_Band_List>
      <Radiometric_Calibration>
         <Instrument_Calibration>
            <Band_Measurement_List>
               <Band_Spectral_Range>
                  <BAND_ID>P</BAND_ID>
                  <CALIBRATION_DATE>2011-12-17T00:00:00.000Z</CALIBRATION_DATE>
                  <MEASURE_DESC>Spectral range value of raw radiometric Band</MEASURE_DESC>
                  <MEASURE_UNIT>micrometers</MEASURE_UNIT>
                  <MEASURE_UNCERTAINTY>Specification accuracy value</MEASURE_UNCERTAINTY>
                  <MIN>0.460</MIN>
                  <MAX>0.845</MAX>
               </Band_Spectral_Range>
               <Band_Radiance>
                  <BAND_ID>P</BAND_ID>
                  <CALIBRATION_DATE>2012-04-21T00:00:01.000Z</CALIBRATION_DATE>
                  <MEASURE_DESC>Raw radiometric count (DN) to TOA Radiance (L). Formulae L=DN/GAIN+BIAS</MEASURE_DESC>
                  <MEASURE_UNIT>watt/m2/steradians/micrometers</MEASURE_UNIT>
                  <MEASURE_UNCERTAINTY>Specification accuracy value</MEASURE_UNCERTAINTY>
                  <GAIN>11.36</GAIN>
                  <BIAS>0</BIAS>
               </Band_Radiance>
               <Band_Solar_Irradiance>
                  <BAND_ID>P</BAND_ID>
                  <CALIBRATION_DATE>2011-12-17T00:00:00.000Z</CALIBRATION_DATE>
                  <MEASURE_DESC>Solar irradiance value of raw radiometric Band</MEASURE_DESC>
                  <MEASURE_UNIT>watt/m2/micron</MEASURE_UNIT>
                  <MEASURE_UNCERTAINTY>Specification</MEASURE_UNCERTAINTY>
                  <VALUE>1548</VALUE>
               </Band_Solar_Irradiance>
            </Band_Measurement_List>
         </Instrument_Calibration>
      </Radiometric_Calibration>
  </Radiometric_Data>
  <Geometric_Data>
      <Refined_Model>
         <MODEL_USED>SENSOR</MODEL_USED>
         <Coordinate_Reference_System>
            <Geodetic_CRS>
               <GEODETIC_CRS_TYPE>GEOCENTRIC</GEODETIC_CRS_TYPE>
               <GEODETIC_CRS_NAME>WGS 1984</GEODETIC_CRS_NAME>
               <GEODETIC_CRS_CODE>urn:ogc:def:crs:EPSG::4978</GEODETIC_CRS_CODE>
               <Coordinate_System>
                  <CS_TYPE>CARTESIAN</CS_TYPE>
                  <CS_NAME>Earth centered, earth fixed, righthanded 3D coordinate system, consisting of 3 orthogonal axes with X and Y axes in the equatorial plane, positive Z-axis parallel to mean earth rotation axis and pointing towards North Pole. UoM: m</CS_NAME>
                  <CS_CODE>urn:ogc:def:cs:EPSG::6500</CS_CODE>
                  <CS_Axes>
                     <CS_Axis>
                        <CS_AXIS_NAME>Geocentric X</CS_AXIS_NAME>
                        <CS_AXIS_ORIENTATION>Geocentre to equator/0degE</CS_AXIS_ORIENTATION>
                        <CS_AXIS_UNIT>m</CS_AXIS_UNIT>
                     </CS_Axis>
                     <CS_Axis>
                        <CS_AXIS_NAME>Geocentric Y</CS_AXIS_NAME>
                        <CS_AXIS_ORIENTATION>Geocentre to equator/90degE</CS_AXIS_ORIENTATION>
                        <CS_AXIS_UNIT>m</CS_AXIS_UNIT>
                     </CS_Axis>
                     <CS_Axis>
                        <CS_AXIS_NAME>Geocentric Z</CS_AXIS_NAME>
                        <CS_AXIS_ORIENTATION>Geocentre to north pole</CS_AXIS_ORIENTATION>
                        <CS_AXIS_UNIT>m</CS_AXIS_UNIT>
                     </CS_Axis>
                  </CS_Axes>
               </Coordinate_System>
               <Geodetic_Datum>
                  <GEODETIC_DATUM_NAME>World Geodetic System 1984</GEODETIC_DATUM_NAME>
                  <GEODETIC_DATUM_CODE>urn:ogc:def:datum:EPSG::6326</GEODETIC_DATUM_CODE>
                  <GEODETIC_DATUM_PARAMETERS>On 20/1/2002 WGS 84 (G1150)</GEODETIC_DATUM_PARAMETERS>
               </Geodetic_Datum>
               <Coordinate_Transformation>
                  <CT_NAME>ITRF to WGS84 transformation parameters</CT_NAME>
                  <CT_SOURCE_CRS_NAME>ITRF 2005</CT_SOURCE_CRS_NAME>
                  <CT_SOURCE_CRS_CODE>urn:ogc:def:crs:EPSG::4896</CT_SOURCE_CRS_CODE>
                  <CT_TARGET_CRS_NAME>WGS 1984</CT_TARGET_CRS_NAME>
                  <CT_TARGET_CRS_CODE>urn:ogc:def:crs:EPSG::4978</CT_TARGET_CRS_CODE>
                  <CT_Parameters>
                     <CT_PARAMETERS_DESC>7-Parameter-Helmert-Transformation derived from : X-axis translation =0m, Y-axis translation=0m, Z-axis translation=0m, X-axis rotation=0m, Y-axis rotation=0m, Z-axis rotation=0m, Scale difference=0</CT_PARAMETERS_DESC>
                  </CT_Parameters>
               </Coordinate_Transformation>
            </Geodetic_CRS>
            <Temporal_CRS>
               <CRS_TABLES version="0.0">ITU</CRS_TABLES>
               <TEMPORAL_CRS_NAME>UTC</TEMPORAL_CRS_NAME>
            </Temporal_CRS>
         </Coordinate_Reference_System>
         <Time>
            <Time_Range>
               <START>2013-03-31T08:39:56.8190000Z</START>
               <END>2013-03-31T08:39:57.9855185Z</END>
            </Time_Range>
            <Time_Stamp>
               <LINE_PERIOD>0.0735</LINE_PERIOD>
            </Time_Stamp>
         </Time>
         <Ephemeris>
            <EPHEMERIS_USED>CORRECTED</EPHEMERIS_USED>
            <Point_List>
               <Point>
                  <LOCATION_XYZ unit="m">3658238.544 2826573.029 5350166.759</LOCATION_XYZ>
                  <VELOCITY_XYZ unit="m/s">5394.171898588073 2096.479192972649 -4783.941522113048</VELOCITY_XYZ>
                  <TIME>2013-03-31T08:37:55.000000Z</TIME>
               </Point>
               <Point>
                  <LOCATION_XYZ unit="m">3824493.766 2879666.494 5203957.807</LOCATION_XYZ>
                  <VELOCITY_XYZ unit="m/s">5272.382997194305 1988.521241382696 -4962.499066112563</VELOCITY_XYZ>
                  <TIME>2013-03-31T08:38:25.000000Z</TIME>
               </Point>
               <Point>
                  <LOCATION_XYZ unit="m">3987120.236 2929139.121 5052466.995</LOCATION_XYZ>
                  <VELOCITY_XYZ unit="m/s">5144.795198186766 1879.096960105933 -5136.0354426587</VELOCITY_XYZ>
                  <TIME>2013-03-31T08:38:55.000000Z</TIME>
               </Point>
               <Point>
                  <LOCATION_XYZ unit="m">4145937.835 2974957.079 4895847.632</LOCATION_XYZ>
                  <VELOCITY_XYZ unit="m/s">5011.530072540045 1768.341540654656 -5304.373305777088</VELOCITY_XYZ>
                  <TIME>2013-03-31T08:39:25.000000Z</TIME>
               </Point>
               <Point>
                  <LOCATION_XYZ unit="m">4300770.12 3017091 4734258.27</LOCATION_XYZ>
                  <VELOCITY_XYZ unit="m/s">4872.715614781715 1656.391033599153 -5467.340374492109</VELOCITY_XYZ>
                  <TIME>2013-03-31T08:39:55.000000Z</TIME>
               </Point>
               <Point>
                  <LOCATION_XYZ unit="m">4451444.523 3055515.99 4567862.553</LOCATION_XYZ>
                  <VELOCITY_XYZ unit="m/s">4728.486218190752 1543.382259077393 -5624.76954582613</VELOCITY_XYZ>
                  <TIME>2013-03-31T08:40:25.000000Z</TIME>
               </Point>
               <Point>
                  <LOCATION_XYZ unit="m">4597792.556 3090211.642 4396829.056</LOCATION_XYZ>
                  <VELOCITY_XYZ unit="m/s">4578.982699844055 1429.452732747886 -5776.499159801751</VELOCITY_XYZ>
                  <TIME>2013-03-31T08:40:55.000000Z</TIME>
               </Point>
               <Point>
                  <LOCATION_XYZ unit="m">4739650.01 3121162.049 4221331.119</LOCATION_XYZ>
                  <VELOCITY_XYZ unit="m/s">4424.352231678553 1314.740494296886 -5922.373386442661</VELOCITY_XYZ>
                  <TIME>2013-03-31T08:41:25.000000Z</TIME>
               </Point>
               <Point>
                  <LOCATION_XYZ unit="m">4876857.154 3148355.802 4041546.664</LOCATION_XYZ>
                  <VELOCITY_XYZ unit="m/s">4264.748067625798 1199.383805952501 -6062.242598768324</VELOCITY_XYZ>
                  <TIME>2013-03-31T08:41:55.000000Z</TIME>
               </Point>
               <Point>
                  <LOCATION_XYZ unit="m">5009258.921 3171785.984 3857658.006</LOCATION_XYZ>
                  <VELOCITY_XYZ unit="m/s">4100.329170058481 1083.520844046958 -6195.963514800183</VELOCITY_XYZ>
                  <TIME>2013-03-31T08:42:25.000000Z</TIME>
               </Point>
            </Point_List>
         </Ephemeris>
         <Attitudes>
            <ATTITUDES_USED>ACCURATE</ATTITUDES_USED>
            <Polynomial_Quaternions>
               <OFFSET>31197.46875</OFFSET>
               <SCALE>0.8125</SCALE>
               <Q0>
                  <DEGREE>3</DEGREE>
                  <COEFFICIENTS>-0.2577052973758306 0.001136960114603852 5.854886125687165e-06 -4.301535375679194e-07</COEFFICIENTS>
               </Q0>
               <Q1>
                  <DEGREE>3</DEGREE>
                  <COEFFICIENTS>-0.8578230774239978 0.0003376040753317742 -1.653821105967466e-06 -4.938136729178769e-08</COEFFICIENTS>
               </Q1>
               <Q2>
                  <DEGREE>3</DEGREE>
                  <COEFFICIENTS>-0.3383996000051565 -0.001117111956085417 5.864137011917701e-06 -1.512248715311832e-07</COEFFICIENTS>
               </Q2>
               <Q3>
                  <DEGREE>3</DEGREE>
                  <COEFFICIENTS>0.2884670831863316 0.0007091800608646538 1.721476634541026e-06 -7.118441805446716e-07</COEFFICIENTS>
               </Q3>
            </Polynomial_Quaternions>
         </Attitudes>
         <Instrument_Configuration>
            <FOCAL_LENGTH>12.9</FOCAL_LENGTH>
            <DETECTOR_SIZE_COL>13e-06</DETECTOR_SIZE_COL>
            <DETECTOR_SIZE_ROW>13e-06</DETECTOR_SIZE_ROW>
         </Instrument_Configuration>
         <Geometric_Calibration>
            <Instrument_Calibration>
               <Swath_Range>
                  <FIRST_COL>1</FIRST_COL>
                  <LAST_COL>40000</LAST_COL>
               </Swath_Range>
               <Polynomial_Look_Angles>
                  <XLOS_0>-0.014222</XLOS_0>
                  <XLOS_1>7.113e-07</XLOS_1>
                  <YLOS_0>8.000000000000001e-05</YLOS_0>
               </Polynomial_Look_Angles>
               <Instrument_Biases>
                  <YAW>0.0</YAW>
                  <PITCH>0.0</PITCH>
                  <ROLL>0.0</ROLL>
               </Instrument_Biases>
            </Instrument_Calibration>
         </Geometric_Calibration>
      </Refined_Model>
      <Use_Area>
         <Located_Geometric_Values>
            <LOCATION_TYPE>Top Center</LOCATION_TYPE>
            <TIME>2013-03-31T08:39:56.906Z</TIME>
            <GEOMETRIC_GLIDING>3.094095845556277</GEOMETRIC_GLIDING>
            <Acquisition_Angles>
               <AZIMUTH_ANGLE>180.1449530715409</AZIMUTH_ANGLE>
               <VIEWING_ANGLE_ACROSS_TRACK unit="deg">-18.52376696094663</VIEWING_ANGLE_ACROSS_TRACK>
               <VIEWING_ANGLE_ALONG_TRACK unit="deg">10.00883522116353</VIEWING_ANGLE_ALONG_TRACK>
               <VIEWING_ANGLE unit="deg">20.74144932320525</VIEWING_ANGLE>
               <INCIDENCE_ANGLE_ALONG_TRACK>-7.698154174815014</INCIDENCE_ANGLE_ALONG_TRACK>
               <INCIDENCE_ANGLE_ACROSS_TRACK>22.02013567289915</INCIDENCE_ANGLE_ACROSS_TRACK>
               <INCIDENCE_ANGLE>23.09467219349365</INCIDENCE_ANGLE>
            </Acquisition_Angles>
            <Solar_Incidences>
               <SUN_AZIMUTH unit="deg">149.599388977834</SUN_AZIMUTH>
               <SUN_ELEVATION unit="deg">49.22290074703253</SUN_ELEVATION>
            </Solar_Incidences>
            <Ground_Sample_Distance>
               <GSD_ACROSS_TRACK unit="m">0.756532873914617</GSD_ACROSS_TRACK>
               <GSD_ALONG_TRACK unit="m">0.8201248868120858</GSD_ALONG_TRACK>
            </Ground_Sample_Distance>
         </Located_Geometric_Values>
         <Located_Geometric_Values>
            <LOCATION_TYPE>Center</LOCATION_TYPE>
            <TIME>2013-03-31T08:39:57.406Z</TIME>
            <GEOMETRIC_GLIDING>3.094897581495774</GEOMETRIC_GLIDING>
            <Acquisition_Angles>
               <AZIMUTH_ANGLE>179.995331275521</AZIMUTH_ANGLE>
               <VIEWING_ANGLE_ACROSS_TRACK unit="deg">-18.47060948252539</VIEWING_ANGLE_ACROSS_TRACK>
               <VIEWING_ANGLE_ALONG_TRACK unit="deg">10.02554447315191</VIEWING_ANGLE_ALONG_TRACK>
               <VIEWING_ANGLE unit="deg">20.70276283363014</VIEWING_ANGLE>
               <INCIDENCE_ANGLE_ALONG_TRACK>-7.666286123673424</INCIDENCE_ANGLE_ALONG_TRACK>
               <INCIDENCE_ANGLE_ACROSS_TRACK>21.9822734416274</INCIDENCE_ANGLE_ACROSS_TRACK>
               <INCIDENCE_ANGLE>23.05061456638582</INCIDENCE_ANGLE>
            </Acquisition_Angles>
            <Solar_Incidences>
               <SUN_AZIMUTH unit="deg">149.5799745694172</SUN_AZIMUTH>
               <SUN_ELEVATION unit="deg">49.25125454398091</SUN_ELEVATION>
            </Solar_Incidences>
            <Ground_Sample_Distance>
               <GSD_ACROSS_TRACK unit="m">0.7560301728885351</GSD_ACROSS_TRACK>
               <GSD_ALONG_TRACK unit="m">0.8196301283638011</GSD_ALONG_TRACK>
            </Ground_Sample_Distance>
         </Located_Geometric_Values>
         <Located_Geometric_Values>
            <LOCATION_TYPE>Bottom Center</LOCATION_TYPE>
            <TIME>2013-03-31T08:39:57.906Z</TIME>
            <GEOMETRIC_GLIDING>3.095307102680746</GEOMETRIC_GLIDING>
            <Acquisition_Angles>
               <AZIMUTH_ANGLE>179.8686780670731</AZIMUTH_ANGLE>
               <VIEWING_ANGLE_ACROSS_TRACK unit="deg">-18.416671857362</VIEWING_ANGLE_ACROSS_TRACK>
               <VIEWING_ANGLE_ALONG_TRACK unit="deg">10.04177435242754</VIEWING_ANGLE_ALONG_TRACK>
               <VIEWING_ANGLE unit="deg">20.66328683814028</VIEWING_ANGLE>
               <INCIDENCE_ANGLE_ALONG_TRACK>-7.643348002462222</INCIDENCE_ANGLE_ALONG_TRACK>
               <INCIDENCE_ANGLE_ACROSS_TRACK>21.94085501778968</INCIDENCE_ANGLE_ACROSS_TRACK>
               <INCIDENCE_ANGLE>23.00566828160935</INCIDENCE_ANGLE>
            </Acquisition_Angles>
            <Solar_Incidences>
               <SUN_AZIMUTH unit="deg">149.5607374645685</SUN_AZIMUTH>
               <SUN_ELEVATION unit="deg">49.27961781442229</SUN_ELEVATION>
            </Solar_Incidences>
            <Ground_Sample_Distance>
               <GSD_ACROSS_TRACK unit="m">0.7555528723073611</GSD_ACROSS_TRACK>
               <GSD_ALONG_TRACK unit="m">0.8191265029760616</GSD_ALONG_TRACK>
            </Ground_Sample_Distance>
         </Located_Geometric_Values>
      </Use_Area>
  </Geometric_Data>
  <Quality_Assessment>
      <Imaging_Quality_Measurement>
         <QUALITY_TABLES>PHR</QUALITY_TABLES>
         <MEASURE_NAME>Cloud_Cotation (CLD)</MEASURE_NAME>
         <MEASURE_TYPE>AUTOMATIC</MEASURE_TYPE>
         <Quality_Mask>
            <Component>
               <COMPONENT_TITLE>Cloud_Cotation Mask</COMPONENT_TITLE>
               <COMPONENT_CONTENT>GML MASK</COMPONENT_CONTENT>
               <COMPONENT_TYPE>ENCAPSULATED</COMPONENT_TYPE>
               <COMPONENT_PATH href="MASKS/CLD_PHR1A_P_201303310839568_SEN_620285101-001_MSK.GML"/>
            </Component>
         </Quality_Mask>
      </Imaging_Quality_Measurement>
      <Imaging_Quality_Measurement>
         <QUALITY_TABLES>PHR</QUALITY_TABLES>
         <MEASURE_NAME>Detector_Quality (DET)</MEASURE_NAME>
         <MEASURE_TYPE>AUTOMATIC</MEASURE_TYPE>
         <Quality_Mask>
            <Component>
               <COMPONENT_TITLE>Detector_Quality Mask</COMPONENT_TITLE>
               <COMPONENT_CONTENT>GML MASK</COMPONENT_CONTENT>
               <COMPONENT_TYPE>ENCAPSULATED</COMPONENT_TYPE>
               <COMPONENT_PATH href="MASKS/DET_PHR1A_P_201303310839568_SEN_620285101-001_MSK.GML"/>
            </Component>
         </Quality_Mask>
      </Imaging_Quality_Measurement>
      <Imaging_Quality_Measurement>
         <QUALITY_TABLES>PHR</QUALITY_TABLES>
         <MEASURE_NAME>Technical_Index (QTE)</MEASURE_NAME>
         <MEASURE_TYPE>AUTOMATIC</MEASURE_TYPE>
         <Quality_Mask>
            <Component>
               <COMPONENT_TITLE>Technical_Index Mask</COMPONENT_TITLE>
               <COMPONENT_CONTENT>GML MASK</COMPONENT_CONTENT>
               <COMPONENT_TYPE>ENCAPSULATED</COMPONENT_TYPE>
               <COMPONENT_PATH href="MASKS/QTE_PHR1A_P_201303310839568_SEN_620285101-001_MSK.GML"/>
            </Component>
         </Quality_Mask>
      </Imaging_Quality_Measurement>
      <Imaging_Quality_Measurement>
         <QUALITY_TABLES>PHR</QUALITY_TABLES>
         <MEASURE_NAME>Area_Of_Interest (ROI)</MEASURE_NAME>
         <MEASURE_TYPE>AUTOMATIC</MEASURE_TYPE>
         <Quality_Mask>
            <Component>
               <COMPONENT_TITLE>Area_Of_Interest Mask</COMPONENT_TITLE>
               <COMPONENT_CONTENT>GML MASK</COMPONENT_CONTENT>
               <COMPONENT_TYPE>ENCAPSULATED</COMPONENT_TYPE>
               <COMPONENT_PATH href="MASKS/ROI_PHR1A_P_201303310839568_SEN_620285101-001_MSK.GML"/>
            </Component>
         </Quality_Mask>
      </Imaging_Quality_Measurement>
  </Quality_Assessment>
  <Dataset_Sources>
      <Source_Identification>
         <SOURCE_ID>DS_PHR1A_201303310839568_FR1_PX_E031N41_1208_00729</SOURCE_ID>
         <SOURCE_TYPE>Strip_Source</SOURCE_TYPE>
         <SOURCE_DESCRIPTION>PHR1A Data Strip</SOURCE_DESCRIPTION>
         <Strip_Source>
            <MISSION>PHR</MISSION>
            <MISSION_INDEX>1A</MISSION_INDEX>
            <INSTRUMENT>PHR</INSTRUMENT>
            <INSTRUMENT_INDEX>1A</INSTRUMENT_INDEX>
            <IMAGING_DATE>2013-03-31</IMAGING_DATE>
            <IMAGING_TIME>08:39:56.8Z</IMAGING_TIME>
            <BAND_MODE>PX</BAND_MODE>
         </Strip_Source>
         <Component>
            <COMPONENT_TITLE>Strip Source</COMPONENT_TITLE>
            <COMPONENT_CONTENT>Lineage Information</COMPONENT_CONTENT>
            <COMPONENT_TYPE version="2.0">DIMAP</COMPONENT_TYPE>
            <COMPONENT_PATH href="LINEAGE/STRIP_DS_PHR1A_201303310839568_FR1_PX_E031N41_1208_00729_DIM.XML"/>
         </Component>
      </Source_Identification>
  </Dataset_Sources>
</Dimap_Document>